{
    "location": "Guangzhou",
    "species": "PM2.5",
    "message": "200",
    "status": "200",
    "metrics": {
        "latest_training": "2025-03-27T23:09:03.081397",
        "validation_score": "N/A",
        "total_observation": 264,
        "performance": "N/A",
        "start_date": "2025-03-17T01:00:00",
        "end_date": "2025-03-29T22:00:00"
    },
    "forecasts": [
        {
            "time": "2025-03-17T01:00:00",
            "value": 45.61531066894531
        },
        {
            "time": "2025-03-17T04:00:00",
            "value": 45.73032379150391
        },
        {
            "time": "2025-03-17T07:00:00",
            "value": 44.6736946105957
        },
        {
            "time": "2025-03-17T10:00:00",
            "value": 46.27505111694336
        },
        {
            "time": "2025-03-17T13:00:00",
            "value": 51.10816955566406
        },
        {
            "time": "2025-03-17T16:00:00",
            "value": 50.44845581054688
        },
        {
            "time": "2025-03-17T19:00:00",
            "value": 47.91130828857422
        },
        {
            "time": "2025-03-17T22:00:00",
            "value": 46.81053924560547
        },
        {
            "time": "2025-03-18T01:00:00",
            "value": 29.15178108215332
        },
        {
            "time": "2025-03-18T04:00:00",
            "value": 27.745132446289062
        },
        {
            "time": "2025-03-18T07:00:00",
            "value": 26.27321052551269
        },
        {
            "time": "2025-03-18T10:00:00",
            "value": 28.117626190185547
        },
        {
            "time": "2025-03-18T13:00:00",
            "value": 32.446556091308594
        },
        {
            "time": "2025-03-18T16:00:00",
            "value": 33.4158821105957
        },
        {
            "time": "2025-03-18T19:00:00",
            "value": 32.10556411743164
        },
        {
            "time": "2025-03-18T22:00:00",
            "value": 31.29762840270996
        },
        {
            "time": "2025-03-19T01:00:00",
            "value": 27.136512756347656
        },
        {
            "time": "2025-03-19T04:00:00",
            "value": 25.91694641113281
        },
        {
            "time": "2025-03-19T07:00:00",
            "value": 25.68312263488769
        },
        {
            "time": "2025-03-19T10:00:00",
            "value": 28.89270782470703
        },
        {
            "time": "2025-03-19T13:00:00",
            "value": 34.62335586547852
        },
        {
            "time": "2025-03-19T16:00:00",
            "value": 36.18476867675781
        },
        {
            "time": "2025-03-19T19:00:00",
            "value": 34.606388092041016
        },
        {
            "time": "2025-03-19T22:00:00",
            "value": 33.17671203613281
        },
        {
            "time": "2025-03-18T01:00:00",
            "value": 43.22683334350586
        },
        {
            "time": "2025-03-18T04:00:00",
            "value": 42.14618682861328
        },
        {
            "time": "2025-03-18T07:00:00",
            "value": 39.48319625854492
        },
        {
            "time": "2025-03-18T10:00:00",
            "value": 37.62779235839844
        },
        {
            "time": "2025-03-18T13:00:00",
            "value": 38.43254089355469
        },
        {
            "time": "2025-03-18T16:00:00",
            "value": 36.33905792236328
        },
        {
            "time": "2025-03-18T19:00:00",
            "value": 34.32768249511719
        },
        {
            "time": "2025-03-18T22:00:00",
            "value": 34.217010498046875
        },
        {
            "time": "2025-03-19T01:00:00",
            "value": 29.60040664672852
        },
        {
            "time": "2025-03-19T04:00:00",
            "value": 28.02644729614257
        },
        {
            "time": "2025-03-19T07:00:00",
            "value": 26.80728530883789
        },
        {
            "time": "2025-03-19T10:00:00",
            "value": 29.78748321533203
        },
        {
            "time": "2025-03-19T13:00:00",
            "value": 35.49955368041992
        },
        {
            "time": "2025-03-19T16:00:00",
            "value": 37.482566833496094
        },
        {
            "time": "2025-03-19T19:00:00",
            "value": 36.10260772705078
        },
        {
            "time": "2025-03-19T22:00:00",
            "value": 34.848167419433594
        },
        {
            "time": "2025-03-20T01:00:00",
            "value": 34.61005401611328
        },
        {
            "time": "2025-03-20T04:00:00",
            "value": 32.75968170166016
        },
        {
            "time": "2025-03-20T07:00:00",
            "value": 30.986133575439453
        },
        {
            "time": "2025-03-20T10:00:00",
            "value": 32.62636947631836
        },
        {
            "time": "2025-03-20T13:00:00",
            "value": 37.02686309814453
        },
        {
            "time": "2025-03-20T16:00:00",
            "value": 38.462921142578125
        },
        {
            "time": "2025-03-20T19:00:00",
            "value": 37.70446014404297
        },
        {
            "time": "2025-03-20T22:00:00",
            "value": 37.28470993041992
        },
        {
            "time": "2025-03-19T01:00:00",
            "value": 31.821334838867188
        },
        {
            "time": "2025-03-19T04:00:00",
            "value": 30.893693923950195
        },
        {
            "time": "2025-03-19T07:00:00",
            "value": 29.312774658203125
        },
        {
            "time": "2025-03-19T10:00:00",
            "value": 29.388851165771484
        },
        {
            "time": "2025-03-19T13:00:00",
            "value": 31.3723201751709
        },
        {
            "time": "2025-03-19T16:00:00",
            "value": 30.69203186035156
        },
        {
            "time": "2025-03-19T19:00:00",
            "value": 29.645755767822266
        },
        {
            "time": "2025-03-19T22:00:00",
            "value": 29.65003204345703
        },
        {
            "time": "2025-03-20T01:00:00",
            "value": 33.91826629638672
        },
        {
            "time": "2025-03-20T04:00:00",
            "value": 32.970985412597656
        },
        {
            "time": "2025-03-20T07:00:00",
            "value": 32.29888916015625
        },
        {
            "time": "2025-03-20T10:00:00",
            "value": 36.8360595703125
        },
        {
            "time": "2025-03-20T13:00:00",
            "value": 44.4744987487793
        },
        {
            "time": "2025-03-20T16:00:00",
            "value": 47.78706359863281
        },
        {
            "time": "2025-03-20T19:00:00",
            "value": 46.04059600830078
        },
        {
            "time": "2025-03-20T22:00:00",
            "value": 43.63414764404297
        },
        {
            "time": "2025-03-21T01:00:00",
            "value": 29.13712310791016
        },
        {
            "time": "2025-03-21T04:00:00",
            "value": 27.865306854248047
        },
        {
            "time": "2025-03-21T07:00:00",
            "value": 27.09473419189453
        },
        {
            "time": "2025-03-21T10:00:00",
            "value": 29.211153030395508
        },
        {
            "time": "2025-03-21T13:00:00",
            "value": 33.56348419189453
        },
        {
            "time": "2025-03-21T16:00:00",
            "value": 34.37485122680664
        },
        {
            "time": "2025-03-21T19:00:00",
            "value": 32.9798583984375
        },
        {
            "time": "2025-03-21T22:00:00",
            "value": 32.1435546875
        },
        {
            "time": "2025-03-20T01:00:00",
            "value": 32.281253814697266
        },
        {
            "time": "2025-03-20T04:00:00",
            "value": 31.623857498168945
        },
        {
            "time": "2025-03-20T07:00:00",
            "value": 30.439022064208984
        },
        {
            "time": "2025-03-20T10:00:00",
            "value": 31.02967071533203
        },
        {
            "time": "2025-03-20T13:00:00",
            "value": 33.61809539794922
        },
        {
            "time": "2025-03-20T16:00:00",
            "value": 33.01170349121094
        },
        {
            "time": "2025-03-20T19:00:00",
            "value": 31.70173072814941
        },
        {
            "time": "2025-03-20T22:00:00",
            "value": 31.41534805297852
        },
        {
            "time": "2025-03-21T01:00:00",
            "value": 33.03832244873047
        },
        {
            "time": "2025-03-21T04:00:00",
            "value": 31.685901641845703
        },
        {
            "time": "2025-03-21T07:00:00",
            "value": 30.99856758117676
        },
        {
            "time": "2025-03-21T10:00:00",
            "value": 36.420989990234375
        },
        {
            "time": "2025-03-21T13:00:00",
            "value": 45.25263977050781
        },
        {
            "time": "2025-03-21T16:00:00",
            "value": 49.32707214355469
        },
        {
            "time": "2025-03-21T19:00:00",
            "value": 47.634559631347656
        },
        {
            "time": "2025-03-21T22:00:00",
            "value": 45.08837127685547
        },
        {
            "time": "2025-03-22T01:00:00",
            "value": 27.45817947387696
        },
        {
            "time": "2025-03-22T04:00:00",
            "value": 26.40432929992676
        },
        {
            "time": "2025-03-22T07:00:00",
            "value": 26.066734313964844
        },
        {
            "time": "2025-03-22T10:00:00",
            "value": 28.636249542236328
        },
        {
            "time": "2025-03-22T13:00:00",
            "value": 33.41968536376953
        },
        {
            "time": "2025-03-22T16:00:00",
            "value": 34.282718658447266
        },
        {
            "time": "2025-03-22T19:00:00",
            "value": 32.631980895996094
        },
        {
            "time": "2025-03-22T22:00:00",
            "value": 31.48747634887696
        },
        {
            "time": "2025-03-21T01:00:00",
            "value": 30.14469146728516
        },
        {
            "time": "2025-03-21T04:00:00",
            "value": 29.64283943176269
        },
        {
            "time": "2025-03-21T07:00:00",
            "value": 28.91020393371582
        },
        {
            "time": "2025-03-21T10:00:00",
            "value": 30.677413940429688
        },
        {
            "time": "2025-03-21T13:00:00",
            "value": 34.39981842041016
        },
        {
            "time": "2025-03-21T16:00:00",
            "value": 34.642616271972656
        },
        {
            "time": "2025-03-21T19:00:00",
            "value": 33.75212097167969
        },
        {
            "time": "2025-03-21T22:00:00",
            "value": 33.416900634765625
        },
        {
            "time": "2025-03-22T01:00:00",
            "value": 34.16796112060547
        },
        {
            "time": "2025-03-22T04:00:00",
            "value": 32.62993240356445
        },
        {
            "time": "2025-03-22T07:00:00",
            "value": 31.808263778686523
        },
        {
            "time": "2025-03-22T10:00:00",
            "value": 37.559120178222656
        },
        {
            "time": "2025-03-22T13:00:00",
            "value": 47.006134033203125
        },
        {
            "time": "2025-03-22T16:00:00",
            "value": 51.37010192871094
        },
        {
            "time": "2025-03-22T19:00:00",
            "value": 49.55902099609375
        },
        {
            "time": "2025-03-22T22:00:00",
            "value": 46.904518127441406
        },
        {
            "time": "2025-03-23T01:00:00",
            "value": 36.90708923339844
        },
        {
            "time": "2025-03-23T04:00:00",
            "value": 34.57048797607422
        },
        {
            "time": "2025-03-23T07:00:00",
            "value": 32.26457977294922
        },
        {
            "time": "2025-03-23T10:00:00",
            "value": 33.72542190551758
        },
        {
            "time": "2025-03-23T13:00:00",
            "value": 38.61254119873047
        },
        {
            "time": "2025-03-23T16:00:00",
            "value": 40.56848907470703
        },
        {
            "time": "2025-03-23T19:00:00",
            "value": 40.06944274902344
        },
        {
            "time": "2025-03-23T22:00:00",
            "value": 39.802223205566406
        },
        {
            "time": "2025-03-22T01:00:00",
            "value": 34.352867126464844
        },
        {
            "time": "2025-03-22T04:00:00",
            "value": 33.108863830566406
        },
        {
            "time": "2025-03-22T07:00:00",
            "value": 31.2431640625
        },
        {
            "time": "2025-03-22T10:00:00",
            "value": 32.99505615234375
        },
        {
            "time": "2025-03-22T13:00:00",
            "value": 37.684661865234375
        },
        {
            "time": "2025-03-22T16:00:00",
            "value": 38.00218200683594
        },
        {
            "time": "2025-03-22T19:00:00",
            "value": 36.97201919555664
        },
        {
            "time": "2025-03-22T22:00:00",
            "value": 37.06898498535156
        },
        {
            "time": "2025-03-23T01:00:00",
            "value": 45.736289978027344
        },
        {
            "time": "2025-03-23T04:00:00",
            "value": 44.52326202392578
        },
        {
            "time": "2025-03-23T07:00:00",
            "value": 42.153297424316406
        },
        {
            "time": "2025-03-23T10:00:00",
            "value": 44.72103500366211
        },
        {
            "time": "2025-03-23T13:00:00",
            "value": 51.591835021972656
        },
        {
            "time": "2025-03-23T16:00:00",
            "value": 54.05507659912109
        },
        {
            "time": "2025-03-23T19:00:00",
            "value": 51.94447326660156
        },
        {
            "time": "2025-03-23T22:00:00",
            "value": 49.90751647949219
        },
        {
            "time": "2025-03-24T01:00:00",
            "value": 54.72345352172852
        },
        {
            "time": "2025-03-24T04:00:00",
            "value": 50.725242614746094
        },
        {
            "time": "2025-03-24T07:00:00",
            "value": 45.21871948242188
        },
        {
            "time": "2025-03-24T10:00:00",
            "value": 44.88020324707031
        },
        {
            "time": "2025-03-24T13:00:00",
            "value": 49.24540328979492
        },
        {
            "time": "2025-03-24T16:00:00",
            "value": 51.91335678100586
        },
        {
            "time": "2025-03-24T19:00:00",
            "value": 52.00679016113281
        },
        {
            "time": "2025-03-24T22:00:00",
            "value": 52.48229217529297
        },
        {
            "time": "2025-03-23T01:00:00",
            "value": 62.24169158935547
        },
        {
            "time": "2025-03-23T04:00:00",
            "value": 60.41107940673828
        },
        {
            "time": "2025-03-23T07:00:00",
            "value": 55.73116683959961
        },
        {
            "time": "2025-03-23T10:00:00",
            "value": 54.01837158203125
        },
        {
            "time": "2025-03-23T13:00:00",
            "value": 57.43540191650391
        },
        {
            "time": "2025-03-23T16:00:00",
            "value": 55.38475799560547
        },
        {
            "time": "2025-03-23T19:00:00",
            "value": 52.588905334472656
        },
        {
            "time": "2025-03-23T22:00:00",
            "value": 52.57988357543945
        },
        {
            "time": "2025-03-24T01:00:00",
            "value": 54.67402648925781
        },
        {
            "time": "2025-03-24T04:00:00",
            "value": 52.04629898071289
        },
        {
            "time": "2025-03-24T07:00:00",
            "value": 46.852294921875
        },
        {
            "time": "2025-03-24T10:00:00",
            "value": 44.8587646484375
        },
        {
            "time": "2025-03-24T13:00:00",
            "value": 48.140846252441406
        },
        {
            "time": "2025-03-24T16:00:00",
            "value": 48.79872894287109
        },
        {
            "time": "2025-03-24T19:00:00",
            "value": 47.41413497924805
        },
        {
            "time": "2025-03-24T22:00:00",
            "value": 47.68382263183594
        },
        {
            "time": "2025-03-25T01:00:00",
            "value": 37.96550369262695
        },
        {
            "time": "2025-03-25T04:00:00",
            "value": 35.06505584716797
        },
        {
            "time": "2025-03-25T07:00:00",
            "value": 31.5300407409668
        },
        {
            "time": "2025-03-25T10:00:00",
            "value": 31.10733222961425
        },
        {
            "time": "2025-03-25T13:00:00",
            "value": 32.89122772216797
        },
        {
            "time": "2025-03-25T16:00:00",
            "value": 33.123130798339844
        },
        {
            "time": "2025-03-25T19:00:00",
            "value": 32.582763671875
        },
        {
            "time": "2025-03-25T22:00:00",
            "value": 33.254241943359375
        },
        {
            "time": "2025-03-24T01:00:00",
            "value": 51.69547271728516
        },
        {
            "time": "2025-03-24T04:00:00",
            "value": 49.045928955078125
        },
        {
            "time": "2025-03-24T07:00:00",
            "value": 44.55206298828125
        },
        {
            "time": "2025-03-24T10:00:00",
            "value": 46.04622268676758
        },
        {
            "time": "2025-03-24T13:00:00",
            "value": 52.786529541015625
        },
        {
            "time": "2025-03-24T16:00:00",
            "value": 53.59709167480469
        },
        {
            "time": "2025-03-24T19:00:00",
            "value": 52.778465270996094
        },
        {
            "time": "2025-03-24T22:00:00",
            "value": 53.51432418823242
        },
        {
            "time": "2025-03-25T01:00:00",
            "value": 41.04479217529297
        },
        {
            "time": "2025-03-25T04:00:00",
            "value": 39.20410919189453
        },
        {
            "time": "2025-03-25T07:00:00",
            "value": 35.788368225097656
        },
        {
            "time": "2025-03-25T10:00:00",
            "value": 33.94735336303711
        },
        {
            "time": "2025-03-25T13:00:00",
            "value": 35.3420295715332
        },
        {
            "time": "2025-03-25T16:00:00",
            "value": 34.78998947143555
        },
        {
            "time": "2025-03-25T19:00:00",
            "value": 33.563560485839844
        },
        {
            "time": "2025-03-25T22:00:00",
            "value": 34.043914794921875
        },
        {
            "time": "2025-03-26T01:00:00",
            "value": 27.8711166381836
        },
        {
            "time": "2025-03-26T04:00:00",
            "value": 25.956432342529297
        },
        {
            "time": "2025-03-26T07:00:00",
            "value": 24.133132934570312
        },
        {
            "time": "2025-03-26T10:00:00",
            "value": 24.055923461914062
        },
        {
            "time": "2025-03-26T13:00:00",
            "value": 24.82841110229492
        },
        {
            "time": "2025-03-26T16:00:00",
            "value": 23.78055191040039
        },
        {
            "time": "2025-03-26T19:00:00",
            "value": 22.593366622924805
        },
        {
            "time": "2025-03-26T22:00:00",
            "value": 23.00432586669922
        },
        {
            "time": "2025-03-25T01:00:00",
            "value": 58.29047393798828
        },
        {
            "time": "2025-03-25T04:00:00",
            "value": 55.49895477294922
        },
        {
            "time": "2025-03-25T07:00:00",
            "value": 50.01322937011719
        },
        {
            "time": "2025-03-25T10:00:00",
            "value": 46.28759765625
        },
        {
            "time": "2025-03-25T13:00:00",
            "value": 47.273834228515625
        },
        {
            "time": "2025-03-25T16:00:00",
            "value": 44.42833709716797
        },
        {
            "time": "2025-03-25T19:00:00",
            "value": 42.16564178466797
        },
        {
            "time": "2025-03-25T22:00:00",
            "value": 42.73883819580078
        },
        {
            "time": "2025-03-26T01:00:00",
            "value": 30.6225643157959
        },
        {
            "time": "2025-03-26T04:00:00",
            "value": 29.52333641052246
        },
        {
            "time": "2025-03-26T07:00:00",
            "value": 27.63086700439453
        },
        {
            "time": "2025-03-26T10:00:00",
            "value": 26.60102272033692
        },
        {
            "time": "2025-03-26T13:00:00",
            "value": 27.36746597290039
        },
        {
            "time": "2025-03-26T16:00:00",
            "value": 26.63905334472656
        },
        {
            "time": "2025-03-26T19:00:00",
            "value": 25.76120376586914
        },
        {
            "time": "2025-03-26T22:00:00",
            "value": 26.0313777923584
        },
        {
            "time": "2025-03-27T01:00:00",
            "value": 20.970382690429688
        },
        {
            "time": "2025-03-27T04:00:00",
            "value": 19.44604682922364
        },
        {
            "time": "2025-03-27T07:00:00",
            "value": 18.34272003173828
        },
        {
            "time": "2025-03-27T10:00:00",
            "value": 18.984619140625
        },
        {
            "time": "2025-03-27T13:00:00",
            "value": 20.537841796875
        },
        {
            "time": "2025-03-27T16:00:00",
            "value": 19.90227127075196
        },
        {
            "time": "2025-03-27T19:00:00",
            "value": 19.0009708404541
        },
        {
            "time": "2025-03-27T22:00:00",
            "value": 19.362607955932617
        },
        {
            "time": "2025-03-26T01:00:00",
            "value": 33.381248474121094
        },
        {
            "time": "2025-03-26T04:00:00",
            "value": 33.01981735229492
        },
        {
            "time": "2025-03-26T07:00:00",
            "value": 31.92173767089844
        },
        {
            "time": "2025-03-26T10:00:00",
            "value": 30.45797538757324
        },
        {
            "time": "2025-03-26T13:00:00",
            "value": 30.2377986907959
        },
        {
            "time": "2025-03-26T16:00:00",
            "value": 28.419692993164062
        },
        {
            "time": "2025-03-26T19:00:00",
            "value": 26.94646644592285
        },
        {
            "time": "2025-03-26T22:00:00",
            "value": 26.53390312194824
        },
        {
            "time": "2025-03-27T01:00:00",
            "value": 23.75288200378418
        },
        {
            "time": "2025-03-27T04:00:00",
            "value": 23.185441970825195
        },
        {
            "time": "2025-03-27T07:00:00",
            "value": 22.355587005615234
        },
        {
            "time": "2025-03-27T10:00:00",
            "value": 22.133028030395508
        },
        {
            "time": "2025-03-27T13:00:00",
            "value": 22.82876777648925
        },
        {
            "time": "2025-03-27T16:00:00",
            "value": 22.1381950378418
        },
        {
            "time": "2025-03-27T19:00:00",
            "value": 21.448347091674805
        },
        {
            "time": "2025-03-27T22:00:00",
            "value": 21.42873191833496
        },
        {
            "time": "2025-03-28T01:00:00",
            "value": 28.15639305114746
        },
        {
            "time": "2025-03-28T04:00:00",
            "value": 26.30415344238281
        },
        {
            "time": "2025-03-28T07:00:00",
            "value": 24.56686019897461
        },
        {
            "time": "2025-03-28T10:00:00",
            "value": 24.69510841369629
        },
        {
            "time": "2025-03-28T13:00:00",
            "value": 25.89346504211425
        },
        {
            "time": "2025-03-28T16:00:00",
            "value": 24.98065185546875
        },
        {
            "time": "2025-03-28T19:00:00",
            "value": 23.739479064941406
        },
        {
            "time": "2025-03-28T22:00:00",
            "value": 24.05932235717773
        },
        {
            "time": "2025-03-27T01:00:00",
            "value": 25.903507232666016
        },
        {
            "time": "2025-03-27T04:00:00",
            "value": 25.95472526550293
        },
        {
            "time": "2025-03-27T07:00:00",
            "value": 25.9047794342041
        },
        {
            "time": "2025-03-27T10:00:00",
            "value": 25.883878707885746
        },
        {
            "time": "2025-03-27T13:00:00",
            "value": 26.385906219482425
        },
        {
            "time": "2025-03-27T16:00:00",
            "value": 25.58485984802246
        },
        {
            "time": "2025-03-27T19:00:00",
            "value": 24.81024742126465
        },
        {
            "time": "2025-03-27T22:00:00",
            "value": 24.310272216796875
        },
        {
            "time": "2025-03-28T01:00:00",
            "value": 25.219560623168945
        },
        {
            "time": "2025-03-28T04:00:00",
            "value": 24.92989730834961
        },
        {
            "time": "2025-03-28T07:00:00",
            "value": 24.29242515563965
        },
        {
            "time": "2025-03-28T10:00:00",
            "value": 24.47463607788086
        },
        {
            "time": "2025-03-28T13:00:00",
            "value": 25.6479606628418
        },
        {
            "time": "2025-03-28T16:00:00",
            "value": 24.94315719604492
        },
        {
            "time": "2025-03-28T19:00:00",
            "value": 23.844112396240234
        },
        {
            "time": "2025-03-28T22:00:00",
            "value": 23.39806365966797
        },
        {
            "time": "2025-03-29T01:00:00",
            "value": 29.39107131958008
        },
        {
            "time": "2025-03-29T04:00:00",
            "value": 27.935466766357425
        },
        {
            "time": "2025-03-29T07:00:00",
            "value": 26.54778861999512
        },
        {
            "time": "2025-03-29T10:00:00",
            "value": 27.053146362304688
        },
        {
            "time": "2025-03-29T13:00:00",
            "value": 28.766082763671875
        },
        {
            "time": "2025-03-29T16:00:00",
            "value": 27.961898803710938
        },
        {
            "time": "2025-03-29T19:00:00",
            "value": 26.480607986450195
        },
        {
            "time": "2025-03-29T22:00:00",
            "value": 26.45101547241211
        }
    ]
}