{
    "location": "ArlingtonTX",
    "species": "Ozone",
    "message": "200",
    "status": "200",
    "metrics": {
        "latest_training": "2025-03-16 17:16:11.963259",
        "validation_score": "N/A",
        "total_observation": 127,
        "accuracy": "{\n    \"metrics\": [\n        {\n            \"name\": \"Training R2\",\n            \"value\": \"0.9215456259214176\"\n        },\n        {\n            \"name\": \"Test R2\",\n            \"value\": \"0.9203295208785385\"\n        },\n        {\n            \"name\": \"Training MSE\",\n            \"value\": \"27.28049390639122\"\n        },\n        {\n            \"name\": \"Test MSE\",\n            \"value\": \"27.92795565015331\"\n        },\n        {\n            \"name\": \"Training MAE\",\n            \"value\": \"3.8975876503190703\"\n        },\n        {\n            \"name\": \"Test MAE\",\n            \"value\": \"3.9577425686791723\"\n        }\n    ]\n}",
        "start_date": "2025-03-15 05:00:00",
        "end_date": "2025-03-20 11:00:00"
    },
    "forecasts": [
        {
            "time": "2025-03-15 05:00:00",
            "value": 39.0,
            "predicted": NaN,
            "o3": NaN,
            "pm25": NaN,
            "no2": NaN
        },
        {
            "time": "2025-03-15 06:00:00",
            "value": 30.0,
            "predicted": NaN,
            "o3": NaN,
            "pm25": NaN,
            "no2": NaN
        },
        {
            "time": "2025-03-15 07:00:00",
            "value": 28.0,
            "predicted": NaN,
            "o3": NaN,
            "pm25": NaN,
            "no2": NaN
        },
        {
            "time": "2025-03-15 08:00:00",
            "value": 32.0,
            "predicted": NaN,
            "o3": NaN,
            "pm25": NaN,
            "no2": NaN
        },
        {
            "time": "2025-03-15 09:00:00",
            "value": 34.0,
            "predicted": NaN,
            "o3": NaN,
            "pm25": NaN,
            "no2": NaN
        },
        {
            "time": "2025-03-15 10:00:00",
            "value": 37.0,
            "predicted": NaN,
            "o3": NaN,
            "pm25": NaN,
            "no2": NaN
        },
        {
            "time": "2025-03-15 11:00:00",
            "value": 36.0,
            "predicted": NaN,
            "o3": NaN,
            "pm25": NaN,
            "no2": NaN
        },
        {
            "time": "2025-03-15 12:00:00",
            "value": 35.0,
            "predicted": NaN,
            "o3": 34.75289034327034,
            "pm25": 7.238729476928711,
            "no2": 12.500105839308162
        },
        {
            "time": "2025-03-15 13:00:00",
            "value": 32.0,
            "predicted": NaN,
            "o3": 32.59675196431999,
            "pm25": 7.994022846221924,
            "no2": 12.674729710226984
        },
        {
            "time": "2025-03-15 14:00:00",
            "value": 32.0,
            "predicted": NaN,
            "o3": 35.39026849352922,
            "pm25": 6.342284202575684,
            "no2": 8.149084962383313
        },
        {
            "time": "2025-03-15 15:00:00",
            "value": 34.0,
            "predicted": NaN,
            "o3": 39.697646059266845,
            "pm25": 3.6527414321899414,
            "no2": 4.845799761454828
        },
        {
            "time": "2025-03-15 16:00:00",
            "value": 37.0,
            "predicted": NaN,
            "o3": 43.77216100692749,
            "pm25": 3.0519561767578125,
            "no2": 3.0013431739916996
        },
        {
            "time": "2025-03-15 17:00:00",
            "value": 39.0,
            "predicted": NaN,
            "o3": 47.09000478442249,
            "pm25": 3.348520040512085,
            "no2": 1.9572408138657238
        },
        {
            "time": "2025-03-15 18:00:00",
            "value": 40.0,
            "predicted": NaN,
            "o3": 49.301888793706894,
            "pm25": 4.137772560119629,
            "no2": 1.5570614797510984
        },
        {
            "time": "2025-03-15 19:00:00",
            "value": 41.0,
            "predicted": NaN,
            "o3": 49.59292709827423,
            "pm25": 5.026200771331787,
            "no2": 1.4733866349203595
        },
        {
            "time": "2025-03-15 20:00:00",
            "value": 40.0,
            "predicted": NaN,
            "o3": 48.25415089726448,
            "pm25": 5.122898101806641,
            "no2": 1.5934391583982688
        },
        {
            "time": "2025-03-15 21:00:00",
            "value": 37.0,
            "predicted": NaN,
            "o3": 46.333298087120056,
            "pm25": 4.222405433654785,
            "no2": 1.7262247187233015
        },
        {
            "time": "2025-03-15 22:00:00",
            "value": 37.0,
            "predicted": NaN,
            "o3": 44.23782229423523,
            "pm25": 3.896986961364746,
            "no2": 2.142772626001488
        },
        {
            "time": "2025-03-15 23:00:00",
            "value": 40.0,
            "predicted": NaN,
            "o3": 41.211023926734924,
            "pm25": 4.993972301483154,
            "no2": 3.5579459378709544
        },
        {
            "time": "2025-03-16 00:00:00",
            "value": 38.0,
            "predicted": NaN,
            "o3": 36.67082637548447,
            "pm25": 6.484768867492676,
            "no2": 7.217752617805218
        },
        {
            "time": "2025-03-16 01:00:00",
            "value": 35.0,
            "predicted": NaN,
            "o3": 31.723175197839737,
            "pm25": 8.217697143554688,
            "no2": 11.36504845788977
        },
        {
            "time": "2025-03-16 02:00:00",
            "value": 32.0,
            "predicted": NaN,
            "o3": 28.026988729834557,
            "pm25": 9.721953392028809,
            "no2": 14.435502571075176
        },
        {
            "time": "2025-03-16 03:00:00",
            "value": 27.0,
            "predicted": NaN,
            "o3": 26.135239750146866,
            "pm25": 10.741182327270508,
            "no2": 16.152629456200884
        },
        {
            "time": "2025-03-16 04:00:00",
            "value": NaN,
            "predicted": NaN,
            "o3": 25.989720597863197,
            "pm25": 13.241131782531738,
            "no2": 16.560083082595156
        },
        {
            "time": "2025-03-16 05:00:00",
            "value": 28.0,
            "predicted": NaN,
            "o3": 26.572056555096424,
            "pm25": 15.117798805236816,
            "no2": 16.327252438941287
        },
        {
            "time": "2025-03-16 06:00:00",
            "value": 26.0,
            "predicted": NaN,
            "o3": 27.823583437225352,
            "pm25": 16.27288055419922,
            "no2": 14.959372407474802
        },
        {
            "time": "2025-03-16 07:00:00",
            "value": 24.0,
            "predicted": NaN,
            "o3": 28.347281855189976,
            "pm25": 17.20609474182129,
            "no2": 13.649700036921786
        },
        {
            "time": "2025-03-16 08:00:00",
            "value": 21.0,
            "predicted": NaN,
            "o3": 27.359122967141047,
            "pm25": 20.24176025390625,
            "no2": 13.693356670785306
        },
        {
            "time": "2025-03-16 09:00:00",
            "value": 25.0,
            "predicted": NaN,
            "o3": 25.2653098442579,
            "pm25": 29.032691955566406,
            "no2": 14.173569873321412
        },
        {
            "time": "2025-03-16 10:00:00",
            "value": 24.0,
            "predicted": NaN,
            "o3": 21.83201530669976,
            "pm25": 43.798641204833984,
            "no2": 14.682886906314252
        },
        {
            "time": "2025-03-16 11:00:00",
            "value": 15.0,
            "predicted": NaN,
            "o3": 18.074290508707236,
            "pm25": 57.6301383972168,
            "no2": 15.308620149312446
        },
        {
            "time": "2025-03-16 12:00:00",
            "value": 15.0,
            "predicted": NaN,
            "o3": 16.065344610183274,
            "pm25": 61.5621452331543,
            "no2": 16.385461876211593
        },
        {
            "time": "2025-03-16 13:00:00",
            "value": 23.0,
            "predicted": NaN,
            "o3": 16.065319741187523,
            "pm25": 58.05897903442383,
            "no2": 15.861592927990387
        },
        {
            "time": "2025-03-16 14:00:00",
            "value": 29.0,
            "predicted": NaN,
            "o3": 15.7160684466362,
            "pm25": 55.2484016418457,
            "no2": 14.857510777233074
        },
        {
            "time": "2025-03-16 15:00:00",
            "value": 31.0,
            "predicted": NaN,
            "o3": 33.9350663125515,
            "pm25": 18.40877342224121,
            "no2": 6.20639761805819
        },
        {
            "time": "2025-03-16 16:00:00",
            "value": NaN,
            "predicted": NaN,
            "o3": 39.406586438417435,
            "pm25": 12.44122314453125,
            "no2": 3.943574355957935
        },
        {
            "time": "2025-03-16 17:00:00",
            "value": NaN,
            "predicted": NaN,
            "o3": 42.782630771398544,
            "pm25": 10.659794807434082,
            "no2": 3.1541322886852186
        },
        {
            "time": "2025-03-16 18:00:00",
            "value": NaN,
            "predicted": NaN,
            "o3": 46.21688276529312,
            "pm25": 8.673184394836426,
            "no2": 2.5102093736961706
        },
        {
            "time": "2025-03-16 19:00:00",
            "value": NaN,
            "predicted": NaN,
            "o3": 49.301888793706894,
            "pm25": 7.068785667419434,
            "no2": 2.0700134939488635
        },
        {
            "time": "2025-03-16 20:00:00",
            "value": NaN,
            "predicted": NaN,
            "o3": 51.45557224750519,
            "pm25": 5.6383137702941895,
            "no2": 1.8553725222858475
        },
        {
            "time": "2025-03-16 21:00:00",
            "value": NaN,
            "predicted": NaN,
            "o3": 52.56151780486107,
            "pm25": 4.3962554931640625,
            "no2": 1.939045368715142
        },
        {
            "time": "2025-03-16 22:00:00",
            "value": NaN,
            "predicted": NaN,
            "o3": 52.3286871612072,
            "pm25": 3.7439651489257812,
            "no2": 2.663002929281788
        },
        {
            "time": "2025-03-16 23:00:00",
            "value": NaN,
            "predicted": NaN,
            "o3": 49.12726581096649,
            "pm25": 4.447824478149414,
            "no2": 5.922631718391358
        },
        {
            "time": "2025-03-17 00:00:00",
            "value": NaN,
            "predicted": NaN,
            "o3": 38.300640881061554,
            "pm25": 8.654097557067871,
            "no2": 16.58918513669505
        },
        {
            "time": "2025-03-17 01:00:00",
            "value": NaN,
            "predicted": NaN,
            "o3": 31.141098588705063,
            "pm25": 13.420920372009277,
            "no2": 23.545000615854406
        },
        {
            "time": "2025-03-17 02:00:00",
            "value": NaN,
            "predicted": NaN,
            "o3": 35.157427191734314,
            "pm25": 12.926875114440918,
            "no2": 18.655557099123143
        },
        {
            "time": "2025-03-17 03:00:00",
            "value": NaN,
            "predicted": NaN,
            "o3": 41.21180197103058,
            "pm25": 16.559661865234375,
            "no2": 11.612431016772007
        },
        {
            "time": "2025-03-17 04:00:00",
            "value": NaN,
            "predicted": NaN,
            "o3": 40.978726190132875,
            "pm25": 24.0012264251709,
            "no2": 10.85573142489693
        },
        {
            "time": "2025-03-17 05:00:00",
            "value": NaN,
            "predicted": NaN,
            "o3": 38.41750029209834,
            "pm25": 33.5059928894043,
            "no2": 10.782971848755096
        },
        {
            "time": "2025-03-17 06:00:00",
            "value": NaN,
            "predicted": NaN,
            "o3": 35.79816620913334,
            "pm25": 39.000099182128906,
            "no2": 11.074010153322433
        },
        {
            "time": "2025-03-17 07:00:00",
            "value": NaN,
            "predicted": NaN,
            "o3": 34.28478834166526,
            "pm25": 42.37495040893555,
            "no2": 10.695661245563315
        },
        {
            "time": "2025-03-17 08:00:00",
            "value": NaN,
            "predicted": NaN,
            "o3": 33.82152868880439,
            "pm25": 45.125789642333984,
            "no2": 9.677027179577635
        },
        {
            "time": "2025-03-17 09:00:00",
            "value": NaN,
            "predicted": NaN,
            "o3": 33.134938348666765,
            "pm25": 48.00127029418945,
            "no2": 8.847568011560725
        },
        {
            "time": "2025-03-17 10:00:00",
            "value": NaN,
            "predicted": NaN,
            "o3": 31.841061343129695,
            "pm25": 49.939781188964844,
            "no2": 8.425563358116506
        },
        {
            "time": "2025-03-17 11:00:00",
            "value": NaN,
            "predicted": NaN,
            "o3": 28.60906533896923,
            "pm25": 51.062252044677734,
            "no2": 8.585634425628541
        },
        {
            "time": "2025-03-17 12:00:00",
            "value": NaN,
            "predicted": NaN,
            "o3": 24.068867787718773,
            "pm25": 52.49772262573242,
            "no2": 9.269575329540203
        },
        {
            "time": "2025-03-17 13:00:00",
            "value": NaN,
            "predicted": NaN,
            "o3": 21.507730707526207,
            "pm25": 54.81300735473633,
            "no2": 9.240471499083469
        },
        {
            "time": "2025-03-17 14:00:00",
            "value": NaN,
            "predicted": NaN,
            "o3": 25.844203221936368,
            "pm25": 48.87540054321289,
            "no2": 8.0326616469506
        },
        {
            "time": "2025-03-17 15:00:00",
            "value": NaN,
            "predicted": NaN,
            "o3": 33.9350663125515,
            "pm25": 29.49811553955078,
            "no2": 5.84259751690297
        },
        {
            "time": "2025-03-17 16:00:00",
            "value": NaN,
            "predicted": NaN,
            "o3": 41.56026989221573,
            "pm25": 11.873992919921875,
            "no2": 3.7071035130509244
        },
        {
            "time": "2025-03-17 17:00:00",
            "value": NaN,
            "predicted": NaN,
            "o3": 47.55565896630287,
            "pm25": 6.906291961669922,
            "no2": 2.470190496595137
        },
        {
            "time": "2025-03-17 18:00:00",
            "value": NaN,
            "predicted": NaN,
            "o3": 52.677933126688,
            "pm25": 5.581549644470215,
            "no2": 1.813535099870478
        },
        {
            "time": "2025-03-17 19:00:00",
            "value": NaN,
            "predicted": NaN,
            "o3": 55.995769798755646,
            "pm25": 5.159280776977539,
            "no2": 1.5752474880059708
        },
        {
            "time": "2025-03-17 20:00:00",
            "value": NaN,
            "predicted": NaN,
            "o3": 57.45096132159233,
            "pm25": 5.029107570648193,
            "no2": 1.5879804138307918
        },
        {
            "time": "2025-03-17 21:00:00",
            "value": NaN,
            "predicted": NaN,
            "o3": 57.800207287073135,
            "pm25": 4.971955299377441,
            "no2": 1.8117162214892346
        },
        {
            "time": "2025-03-17 22:00:00",
            "value": NaN,
            "predicted": NaN,
            "o3": 56.75246939063072,
            "pm25": 5.292529106140137,
            "no2": 2.841264112873887
        },
        {
            "time": "2025-03-17 23:00:00",
            "value": NaN,
            "predicted": NaN,
            "o3": 52.852556109428406,
            "pm25": 6.04523229598999,
            "no2": 5.493350219154536
        },
        {
            "time": "2025-03-18 00:00:00",
            "value": NaN,
            "predicted": NaN,
            "o3": 48.48698154091835,
            "pm25": 6.719407558441162,
            "no2": 7.697964932162904
        },
        {
            "time": "2025-03-18 01:00:00",
            "value": NaN,
            "predicted": NaN,
            "o3": 46.91537469625473,
            "pm25": 8.041991233825684,
            "no2": 7.770724508304738
        },
        {
            "time": "2025-03-18 02:00:00",
            "value": NaN,
            "predicted": NaN,
            "o3": 46.68254405260086,
            "pm25": 9.021785736083984,
            "no2": 6.897610038691937
        },
        {
            "time": "2025-03-18 03:00:00",
            "value": NaN,
            "predicted": NaN,
            "o3": 46.62433994440107,
            "pm25": 8.943268775939941,
            "no2": 5.929907676005541
        },
        {
            "time": "2025-03-18 04:00:00",
            "value": NaN,
            "predicted": NaN,
            "o3": 46.15867865709333,
            "pm25": 8.866037368774414,
            "no2": 5.493350663243746
        },
        {
            "time": "2025-03-18 05:00:00",
            "value": NaN,
            "predicted": NaN,
            "o3": 45.40197551250458,
            "pm25": 8.82202434539795,
            "no2": 5.202312358676409
        },
        {
            "time": "2025-03-18 06:00:00",
            "value": NaN,
            "predicted": NaN,
            "o3": 44.587068259716034,
            "pm25": 8.694546699523926,
            "no2": 4.736651071368669
        },
        {
            "time": "2025-03-18 07:00:00",
            "value": NaN,
            "predicted": NaN,
            "o3": 43.77216100692749,
            "pm25": 8.376264572143555,
            "no2": 4.3146459738352405
        },
        {
            "time": "2025-03-18 08:00:00",
            "value": NaN,
            "predicted": NaN,
            "o3": 43.01548273133449,
            "pm25": 7.756062030792236,
            "no2": 4.081815774270581
        },
        {
            "time": "2025-03-18 09:00:00",
            "value": NaN,
            "predicted": NaN,
            "o3": 42.31710093449692,
            "pm25": 7.047103404998779,
            "no2": 3.9581249389186723
        },
        {
            "time": "2025-03-18 10:00:00",
            "value": NaN,
            "predicted": NaN,
            "o3": 41.61852018569334,
            "pm25": 6.739490509033203,
            "no2": 3.994505615168009
        },
        {
            "time": "2025-03-18 11:00:00",
            "value": NaN,
            "predicted": NaN,
            "o3": 40.7454443518418,
            "pm25": 6.885684967041016,
            "no2": 4.227336702911089
        },
        {
            "time": "2025-03-18 12:00:00",
            "value": NaN,
            "predicted": NaN,
            "o3": 39.872247725725174,
            "pm25": 7.293697357177734,
            "no2": 4.598409653056024
        },
        {
            "time": "2025-03-18 13:00:00",
            "value": NaN,
            "predicted": NaN,
            "o3": 39.173755794763565,
            "pm25": 7.247840404510498,
            "no2": 4.991310476043509
        },
        {
            "time": "2025-03-18 14:00:00",
            "value": NaN,
            "predicted": NaN,
            "o3": 40.105078369379044,
            "pm25": 5.696709156036377,
            "no2": 4.147298504619812
        },
        {
            "time": "2025-03-18 15:00:00",
            "value": NaN,
            "predicted": NaN,
            "o3": 42.316969484090805,
            "pm25": 4.6441168785095215,
            "no2": 2.932213361006575
        },
        {
            "time": "2025-03-18 16:00:00",
            "value": NaN,
            "predicted": NaN,
            "o3": 45.63480615615845,
            "pm25": 4.457983493804932,
            "no2": 2.0845642989542057
        },
        {
            "time": "2025-03-18 17:00:00",
            "value": NaN,
            "predicted": NaN,
            "o3": 49.709342420101166,
            "pm25": 4.7183427810668945,
            "no2": 1.5406864672939946
        },
        {
            "time": "2025-03-18 18:00:00",
            "value": NaN,
            "predicted": NaN,
            "o3": 52.91076377034187,
            "pm25": 5.182883262634277,
            "no2": 1.3478734794958314
        },
        {
            "time": "2025-03-18 19:00:00",
            "value": NaN,
            "predicted": NaN,
            "o3": 54.94803190231323,
            "pm25": 5.626070499420166,
            "no2": 1.353330003617259
        },
        {
            "time": "2025-03-18 20:00:00",
            "value": NaN,
            "predicted": NaN,
            "o3": 55.87935447692871,
            "pm25": 6.005841255187988,
            "no2": 1.5206769177211754
        },
        {
            "time": "2025-03-18 21:00:00",
            "value": NaN,
            "predicted": NaN,
            "o3": 56.05397745966911,
            "pm25": 6.29500675201416,
            "no2": 1.8771986187715584
        },
        {
            "time": "2025-03-18 22:00:00",
            "value": NaN,
            "predicted": NaN,
            "o3": 55.23907020688057,
            "pm25": 6.549656867980957,
            "no2": 2.7503137545181744
        },
        {
            "time": "2025-03-18 23:00:00",
            "value": NaN,
            "predicted": NaN,
            "o3": 52.91076377034187,
            "pm25": 6.9173903465271,
            "no2": 4.962204425140726
        },
        {
            "time": "2025-03-19 00:00:00",
            "value": NaN,
            "predicted": NaN,
            "o3": 49.59292709827423,
            "pm25": 7.064089298248291,
            "no2": 7.0213004299546355
        },
        {
            "time": "2025-03-19 01:00:00",
            "value": NaN,
            "predicted": NaN,
            "o3": 46.798959374427795,
            "pm25": 6.736025333404541,
            "no2": 6.715710210158932
        },
        {
            "time": "2025-03-19 02:00:00",
            "value": NaN,
            "predicted": NaN,
            "o3": 45.460183173418045,
            "pm25": 6.3644118309021,
            "no2": 5.478797859836959
        },
        {
            "time": "2025-03-19 03:00:00",
            "value": NaN,
            "predicted": NaN,
            "o3": 43.94678398966789,
            "pm25": 6.249063491821289,
            "no2": 5.195035956973015
        },
        {
            "time": "2025-03-19 04:00:00",
            "value": NaN,
            "predicted": NaN,
            "o3": 41.96772351861,
            "pm25": 6.285852432250977,
            "no2": 5.5079025784721125
        },
        {
            "time": "2025-03-19 05:00:00",
            "value": NaN,
            "predicted": NaN,
            "o3": 39.406586438417435,
            "pm25": 6.531319618225098,
            "no2": 6.504709215704452
        },
        {
            "time": "2025-03-19 06:00:00",
            "value": NaN,
            "predicted": NaN,
            "o3": 35.21563485264778,
            "pm25": 7.396671295166016,
            "no2": 9.094950570442961
        },
        {
            "time": "2025-03-19 07:00:00",
            "value": NaN,
            "predicted": NaN,
            "o3": 32.47987478971481,
            "pm25": 7.8765363693237305,
            "no2": 12.529202564337538
        },
        {
            "time": "2025-03-19 08:00:00",
            "value": NaN,
            "predicted": NaN,
            "o3": 34.05148873980579,
            "pm25": 12.17934513092041,
            "no2": 7.872589691260146
        },
        {
            "time": "2025-03-19 09:00:00",
            "value": NaN,
            "predicted": NaN,
            "o3": 32.421667128801346,
            "pm25": 14.345170021057129,
            "no2": 4.758480720568059
        },
        {
            "time": "2025-03-19 10:00:00",
            "value": NaN,
            "predicted": NaN,
            "o3": 32.307021058386454,
            "pm25": 9.86617374420166,
            "no2": 4.05998923369566
        },
        {
            "time": "2025-03-19 11:00:00",
            "value": NaN,
            "predicted": NaN,
            "o3": 33.17836672067642,
            "pm25": 8.075553894042969,
            "no2": 3.965402672889695
        },
        {
            "time": "2025-03-19 12:00:00",
            "value": NaN,
            "predicted": NaN,
            "o3": 34.40072759985924,
            "pm25": 6.0250654220581055,
            "no2": 4.067265191309843
        },
        {
            "time": "2025-03-19 13:00:00",
            "value": NaN,
            "predicted": NaN,
            "o3": 34.924596548080444,
            "pm25": 5.07113790512085,
            "no2": 3.7616745274249297
        },
        {
            "time": "2025-03-19 14:00:00",
            "value": NaN,
            "predicted": NaN,
            "o3": 35.390257835388184,
            "pm25": 5.640129566192627,
            "no2": 3.1686833157351657
        },
        {
            "time": "2025-03-19 15:00:00",
            "value": NaN,
            "predicted": NaN,
            "o3": 37.48573362827301,
            "pm25": 6.265194416046143,
            "no2": 2.6884698911544547
        },
        {
            "time": "2025-03-19 16:00:00",
            "value": NaN,
            "predicted": NaN,
            "o3": 39.4647940993309,
            "pm25": 6.545184135437012,
            "no2": 2.153686784467368
        },
        {
            "time": "2025-03-19 17:00:00",
            "value": NaN,
            "predicted": NaN,
            "o3": 41.15281626582146,
            "pm25": 5.705948829650879,
            "no2": 1.813535321915083
        },
        {
            "time": "2025-03-19 18:00:00",
            "value": NaN,
            "predicted": NaN,
            "o3": 42.72442311048508,
            "pm25": 4.995168685913086,
            "no2": 1.6916628098329056
        },
        {
            "time": "2025-03-19 19:00:00",
            "value": NaN,
            "predicted": NaN,
            "o3": 44.121406972408295,
            "pm25": 5.856301307678223,
            "no2": 1.7425944021098871
        },
        {
            "time": "2025-03-19 20:00:00",
            "value": NaN,
            "predicted": NaN,
            "o3": 45.34376785159111,
            "pm25": 6.522119045257568,
            "no2": 1.8844752425195566
        },
        {
            "time": "2025-03-19 21:00:00",
            "value": NaN,
            "predicted": NaN,
            "o3": 45.693013817071915,
            "pm25": 5.9965739250183105,
            "no2": 2.1645993886210135
        },
        {
            "time": "2025-03-19 22:00:00",
            "value": NaN,
            "predicted": NaN,
            "o3": 45.16914486885071,
            "pm25": 6.465298652648926,
            "no2": 2.7393995960522943
        },
        {
            "time": "2025-03-19 23:00:00",
            "value": NaN,
            "predicted": NaN,
            "o3": 41.90951585769653,
            "pm25": 8.03821086883545,
            "no2": 5.784387191454243
        },
        {
            "time": "2025-03-20 00:00:00",
            "value": NaN,
            "predicted": NaN,
            "o3": 31.89779818058014,
            "pm25": 8.826095581054688,
            "no2": 15.046680346131325
        },
        {
            "time": "2025-03-20 01:00:00",
            "value": NaN,
            "predicted": NaN,
            "o3": 23.981556296348572,
            "pm25": 10.54528522491455,
            "no2": 21.740561351180077
        },
        {
            "time": "2025-03-20 02:00:00",
            "value": NaN,
            "predicted": NaN,
            "o3": 20.867446437478065,
            "pm25": 17.045101165771484,
            "no2": 23.632312107224607
        },
        {
            "time": "2025-03-20 03:00:00",
            "value": NaN,
            "predicted": NaN,
            "o3": 17.98616722226143,
            "pm25": 29.063858032226562,
            "no2": 24.82556915595069
        },
        {
            "time": "2025-03-20 04:00:00",
            "value": NaN,
            "predicted": NaN,
            "o3": 13.504177331924438,
            "pm25": 46.98216247558594,
            "no2": 26.862837287922048
        },
        {
            "time": "2025-03-20 05:00:00",
            "value": NaN,
            "predicted": NaN,
            "o3": 8.236384019255638,
            "pm25": 66.22389221191406,
            "no2": 29.71501267268195
        },
        {
            "time": "2025-03-20 06:00:00",
            "value": NaN,
            "predicted": NaN,
            "o3": 4.241896611745233,
            "pm25": 78.09558868408203,
            "no2": 32.07242471603422
        },
        {
            "time": "2025-03-20 07:00:00",
            "value": NaN,
            "predicted": NaN,
            "o3": 3.350582922223566,
            "pm25": 80.47325134277344,
            "no2": 32.53808600334196
        },
        {
            "time": "2025-03-20 08:00:00",
            "value": NaN,
            "predicted": NaN,
            "o3": 4.365579897580574,
            "pm25": 77.9867935180664,
            "no2": 31.37393278507261
        },
        {
            "time": "2025-03-20 09:00:00",
            "value": NaN,
            "predicted": NaN,
            "o3": 5.624326782083244,
            "pm25": 74.371826171875,
            "no2": 29.744120055852363
        },
        {
            "time": "2025-03-20 10:00:00",
            "value": NaN,
            "predicted": NaN,
            "o3": 7.357211728731272,
            "pm25": 69.87808990478516,
            "no2": 27.474023056583974
        },
        {
            "time": "2025-03-20 11:00:00",
            "value": NaN,
            "predicted": NaN,
            "o3": 9.502400644123554,
            "pm25": 65.62572479248047,
            "no2": 24.85467831547794
        }
    ]
}